LICENSE
MANIFEST.in
README.md
setup.py
bin/c4p
c4p/__init__.py
c4p/atm.py
c4p/case.py
c4p/lnd.py
c4p/mapping.py
c4p/ocn.py
c4p/pp.py
c4p/rof.py
c4p/rotation.py
c4p/utils.py
c4p/visual.py
c4p.egg-info/PKG-INFO
c4p.egg-info/SOURCES.txt
c4p.egg-info/dependency_links.txt
c4p.egg-info/not-zip-safe
c4p.egg-info/requires.txt
c4p.egg-info/top_level.txt
c4p/src/atm/add_SGH30_paleo.ncl
c4p/src/atm/definesurf
c4p/src/atm/interpic
c4p/src/atm/mk_10min_definesurf_input_paleo.ncl
c4p/src/atm/modify_aerosol_input_template.ncl
c4p/src/atm/sol_constant_paleo.ncl
c4p/src/atm/sst_cami_create_template.ncl
c4p/src/atm/definesurf_src/Makefile
c4p/src/atm/definesurf_src/ao.f90
c4p/src/atm/definesurf_src/ao_i.f90
c4p/src/atm/definesurf_src/area_ave.f90
c4p/src/atm/definesurf_src/binf2c.f90
c4p/src/atm/definesurf_src/cell_area.f90
c4p/src/atm/definesurf_src/chkdims.f90
c4p/src/atm/definesurf_src/endrun.f90
c4p/src/atm/definesurf_src/fmain.f90
c4p/src/atm/definesurf_src/handle_error.f90
c4p/src/atm/definesurf_src/inimland.f90
c4p/src/atm/definesurf_src/interplandm.f90
c4p/src/atm/definesurf_src/lininterp.f90
c4p/src/atm/definesurf_src/map2f.f90
c4p/src/atm/definesurf_src/map_i.f90
c4p/src/atm/definesurf_src/max_ovr.f90
c4p/src/atm/definesurf_src/sghphis.f90
c4p/src/atm/definesurf_src/shr_kind_mod.f90
c4p/src/atm/definesurf_src/sm121.f90
c4p/src/atm/definesurf_src/terrain_filter.f90
c4p/src/atm/definesurf_src/varf2c.f90
c4p/src/atm/definesurf_src/wrap_nf.f90
c4p/src/atm/interpic_src/Makefile
c4p/src/atm/interpic_src/README
c4p/src/atm/interpic_src/addglobal.F90
c4p/src/atm/interpic_src/compare_var.F90
c4p/src/atm/interpic_src/control.F90
c4p/src/atm/interpic_src/cpvar.F90
c4p/src/atm/interpic_src/dimensions.F90
c4p/src/atm/interpic_src/driver.F90
c4p/src/atm/interpic_src/err_exit.F90
c4p/src/atm/interpic_src/fill_positions.F90
c4p/src/atm/interpic_src/fmain.F90
c4p/src/atm/interpic_src/handle_special_cases.F90
c4p/src/atm/interpic_src/interp.F90
c4p/src/atm/interpic_src/interpolate_data.F90
c4p/src/atm/interpic_src/is_special_case.F90
c4p/src/atm/interpic_src/shr_kind_mod.F90
c4p/src/atm/interpic_src/wrap_nf.F90
