Metadata-Version: 2.1
Name: c4p
Version: 2025.5.22
Summary: c4p: CESM for Paleo
Home-page: https://github.com/fzhu2e/cesm4paleo
Author: Feng Zhu, Jiang Zhu
Author-email: fengzhu@ucar.edu, jiangzhu@ucar.edu
License: MIT
Keywords: CESM,paleoclimate
Classifier: Natural Language :: English
Classifier: Programming Language :: Python :: 3.9
Classifier: Programming Language :: Python :: 3.10
Classifier: Programming Language :: Python :: 3.11
License-File: LICENSE
Requires-Dist: colorama
Requires-Dist: tqdm
Requires-Dist: xarray
Requires-Dist: netCDF4
Requires-Dist: nc-time-axis
Requires-Dist: dask
Requires-Dist: sh
Requires-Dist: pygplates
